dropgen/IRDSObject.py
dropgen/IRDSTable.py
dropgen/IRDSValue.py
dropgen/RDSItem.py
dropgen/RDSNullValue.py
dropgen/RDSObject.py
dropgen/RDSTable.py
dropgen/RDSValue.py
dropgen/__init__.py
drop_generator-0.0.35.dist-info/LICENSE
drop_generator-0.0.35.dist-info/METADATA
drop_generator-0.0.35.dist-info/WHEEL
drop_generator-0.0.35.dist-info/top_level.txt
drop_generator-0.0.35.dist-info/RECORD
