Metadata-Version: 2.1
Name: drop-generator
Version: 0.0.35
Summary: RPG Loot Drop Engine
Home-page: https://gitlab.com/ramencatz/python-loot
Author: Mascha Loomis
Author-email: mascha.loomis@gmail.com
License: MIT
Platform: UNKNOWN
Classifier: License :: OSI Approved :: MIT License
Classifier: Programming Language :: Python :: 3
Classifier: Topic :: Games/Entertainment
Classifier: Topic :: Games/Entertainment :: Role-Playing
Classifier: Topic :: Utilities
Requires-Python: >=3
